bionemo/__init__.py
bionemo/version.py
bionemo/api/__init__.py
bionemo/api/api.py
bionemo/api/error.py
bionemo/api/request_id.py
bionemo/api/response_handler.py
bionemo/api/task_tracker.py
bionemo/api/version.py
bionemo/cli/README.md
bionemo/cli/__init__.py
bionemo/cli/cli.py
docs/Makefile
docs/README.md
docs/conf.py
docs/index.rst
docs/release_notes.md
docs/templates/custom.css
scripts/check_bionemo.py
scripts/readme_script.py
scripts/test_data/6a87_ligand.sdf
scripts/test_data/6a87_protein_processed.pdb
bionemo-0.3.1.post2.dist-info/LICENSE.md
bionemo-0.3.1.post2.dist-info/METADATA
bionemo-0.3.1.post2.dist-info/WHEEL
bionemo-0.3.1.post2.dist-info/entry_points.txt
bionemo-0.3.1.post2.dist-info/top_level.txt
bionemo-0.3.1.post2.dist-info/RECORD
