Metadata-Version: 2.2
Name: bionemo
Version: 0.3.1.post2
Summary: [DEPRECATED] Python client for the BioNeMo Service
Author-email: NVIDIA Bionemo <bionemofeedback@nvidia.com>
Maintainer-email: Kevin Boyd <kboyd@nvidia.com>
License: Copyright (c) 2023 NVIDIA CORPORATION & AFFILIATES. All rights reserved.
Project-URL: Homepage, https://www.nvidia.com/en-us/clara/bionemo/
Project-URL: Documentation, https://developer.nvidia.com/docs/bionemo-service/index.html
Project-URL: Examples, https://github.com/NVIDIA/BioNeMo/tree/main/examples/service
Keywords: bionemo
Classifier: Development Status :: 4 - Beta
Classifier: Programming Language :: Python :: 3
Classifier: Programming Language :: Python :: 3.8
Classifier: Programming Language :: Python :: 3.9
Classifier: Programming Language :: Python :: 3.10
Classifier: Programming Language :: Python :: 3.11
License-File: LICENSE.md
Requires-Dist: click>=8.1
Requires-Dist: h5py
Requires-Dist: numpy
Requires-Dist: requests
Requires-Dist: requests_futures
Requires-Dist: typing_extensions
Provides-Extra: devtools
Requires-Dist: pytest; extra == "devtools"
Requires-Dist: pytest-cov>=2.8.1; extra == "devtools"
Requires-Dist: pytest-json-report; extra == "devtools"
Requires-Dist: pytest-parallel; extra == "devtools"
